CHANGELOG.rst
LICENSE
MANIFEST.in
README.rst
setup.cfg
setup.py
able/__init__.py
able/adapter.py
able/advertising.py
able/dispatcher.py
able/filters.py
able/permissions.py
able/queue.py
able/scan_settings.py
able/structures.py
able/utils.py
able/version.py
able/android/__init__.py
able/android/dispatcher.py
able/android/jni.py
able/src/org/able/BLE.java
able/src/org/able/BLEAdvertiser.java
able/src/org/able/PythonBluetooth.java
able/src/org/able/PythonBluetoothAdvertiser.java
able_recipe_test.egg-info/PKG-INFO
able_recipe_test.egg-info/SOURCES.txt
able_recipe_test.egg-info/dependency_links.txt
able_recipe_test.egg-info/not-zip-safe
able_recipe_test.egg-info/top_level.txt