Metadata-Version: 2.1
Name: able_recipe_test
Version: 1.0.14.12
Summary: Bluetooth Low Energy for Android
Home-page: https://github.com/b3b/able
Author: b3b
Author-email: ash.b3b@gmail.com
License: MIT
Project-URL: Changelog, https://github.com/b3b/able/blob/master/CHANGELOG.rst
Keywords: android ble bluetooth kivy
Classifier: Development Status :: 3 - Alpha
Classifier: License :: OSI Approved :: MIT License
Classifier: Operating System :: Android
Classifier: Topic :: System :: Networking
Classifier: Programming Language :: Python :: 3.6
Classifier: Programming Language :: Python :: 3.7
Classifier: Programming Language :: Python :: 3.8
Classifier: Programming Language :: Python :: 3.9
License-File: LICENSE
